_ringding/__init__.py
_ringding/constants.py
_ringding/messages.py
_ringding/notifications.py
_ringding/server.py
_ringding/client/UnidentifiedClient.py
_ringding/client/__init__.py
_ringding/client/base.py
_ringding/client/rdclient.py
_ringding/resources/__init__.py
_ringding/resources/apibrowser/__init__.py
_ringding/resources/apibrowser/apibrowser.html
_ringding/resources/js/__init__.py
_ringding/resources/js/package-lock.json
_ringding/resources/js/package.json
_ringding/resources/js/ringdingjs.js
_ringding/ws/__init__.py
_ringding/ws/wsserver.py
ringding/__init__.py
ringding/datatypes.py
ringding-0.3.2.dist-info/LICENSE
ringding-0.3.2.dist-info/METADATA
ringding-0.3.2.dist-info/WHEEL
ringding-0.3.2.dist-info/top_level.txt
ringding-0.3.2.dist-info/RECORD
