Metadata-Version: 2.1
Name: ringding
Version: 0.3.2
Summary: Simple framework to create awesome WebSocket APIs
Home-page: https://gitlab.com/pyfox/ringding/
Author: kitsunebi
Author-email: me@pyfox.net
License: UNKNOWN
Project-URL: Documentation, https://gitlab.com/pyfox/ringding/-/wikis/home
Project-URL: Bug Tracker, https://gitlab.com/pyfox/ringding/-/issues
Platform: UNKNOWN
Classifier: Programming Language :: Python :: 3
Classifier: License :: OSI Approved :: MIT License
Classifier: Operating System :: OS Independent
Classifier: Development Status :: 3 - Alpha
Classifier: Environment :: Web Environment
Classifier: Intended Audience :: Developers
Classifier: Programming Language :: Python :: 3.7
Classifier: Programming Language :: Python :: 3.8
Classifier: Programming Language :: Python :: 3.9
License-File: LICENSE
